fmtstr.py
setup.py
formatstring_exploit.egg-info/PKG-INFO
formatstring_exploit.egg-info/SOURCES.txt
formatstring_exploit.egg-info/dependency_links.txt
formatstring_exploit.egg-info/top_level.txt
formatstring_exploit.egg-info/zip-safe