Metadata-Version: 1.0
Name: formatstring-exploit
Version: 0.1
Summary: formatstring-exploit
Home-page: http://github.com/Inndy/formatstring-exploit
Author: Inndy
Author-email: inndy.tw@gmail.com
License: MIT
Keywords: formatstring-exploit
Platform: UNKNOWN
